{
  "version": "2.6.1-RC1",
  "summary": {
    "title": "New Threat Model",
    "owner": "",
    "description": "",
    "id": 0
  },
  "detail": {
    "contributors": [],
    "diagrams": [
      {
        "id": 0,
        "title": "Library Login DFD",
        "diagramType": "STRIDE",
        "placeholder": "New STRIDE diagram description",
        "thumbnail": "./public/content/images/thumbnail.stride.jpg",
        "version": "2.6.1-RC1",
        "cells": [
          {
            "shape": "flow",
            "attrs": {
              "line": {
                "stroke": "#333333",
                "targetMarker": {
                  "name": "block"
                },
                "sourceMarker": {
                  "name": ""
                },
                "strokeDasharray": null
              }
            },
            "width": 200,
            "height": 100,
            "zIndex": 10,
            "connector": "smooth",
            "data": {
              "type": "tm.Flow",
              "name": "Data Flow",
              "description": "",
              "outOfScope": false,
              "isTrustBoundary": false,
              "reasonOutOfScope": "",
              "hasOpenThreats": false,
              "isBidirectional": false,
              "isEncrypted": false,
              "isPublicNetwork": false,
              "protocol": "",
              "threats": [],
              "trustBoundaryIds": []
            },
            "labels": [
              "Data Flow"
            ],
            "id": "4b29a38b-0452-43fc-beac-289617533d80",
            "source": {
              "x": 199,
              "y": -1889
            },
            "target": {
              "cell": "2502d73f-235a-459e-bf50-445ebe2314dc",
              "port": "0dac111f-126c-4a36-bf12-2b23490551f2"
            },
            "vertices": [
              {
                "x": 230,
                "y": -1889
              }
            ]
          },
          {
            "shape": "flow",
            "attrs": {
              "line": {
                "stroke": "#333333",
                "targetMarker": {
                  "name": "block"
                },
                "sourceMarker": {
                  "name": ""
                },
                "strokeDasharray": null
              }
            },
            "width": 200,
            "height": 100,
            "zIndex": 10,
            "connector": "smooth",
            "data": {
              "type": "tm.Flow",
              "name": "Data Flow",
              "description": "",
              "outOfScope": false,
              "isTrustBoundary": false,
              "reasonOutOfScope": "",
              "hasOpenThreats": false,
              "isBidirectional": false,
              "isEncrypted": false,
              "isPublicNetwork": false,
              "protocol": "",
              "threats": [],
              "trustBoundaryIds": []
            },
            "labels": [
              "Data Flow"
            ],
            "id": "5c1d41ac-e15e-4e72-aa40-e40a9cef16fc",
            "source": {
              "x": 390,
              "y": -1879
            },
            "target": {
              "cell": "4d84b8f4-ae10-4bfb-b57b-d267530e4ce3",
              "port": "0dac111f-126c-4a36-bf12-2b23490551f2"
            },
            "vertices": [
              {
                "x": 450,
                "y": -1879
              }
            ]
          },
          {
            "shape": "flow",
            "attrs": {
              "line": {
                "stroke": "#333333",
                "targetMarker": {
                  "name": "block"
                },
                "sourceMarker": {
                  "name": ""
                },
                "strokeDasharray": null
              }
            },
            "width": 200,
            "height": 100,
            "zIndex": 10,
            "connector": "smooth",
            "data": {
              "type": "tm.Flow",
              "name": "Data Flow",
              "description": "",
              "outOfScope": false,
              "isTrustBoundary": false,
              "reasonOutOfScope": "",
              "hasOpenThreats": false,
              "isBidirectional": false,
              "isEncrypted": false,
              "isPublicNetwork": false,
              "protocol": "",
              "threats": [],
              "trustBoundaryIds": []
            },
            "labels": [
              "Data Flow"
            ],
            "id": "3368c750-8045-498b-8ae5-9eb83d5b7e20",
            "source": {
              "x": 602,
              "y": -1880
            },
            "target": {
              "cell": "c1e90d91-4ce7-4b88-b12b-e6b396b4d9f8",
              "port": "b84ce6fb-d361-4789-b422-f2184d977b09"
            }
          },
          {
            "shape": "trust-boundary-curve",
            "width": 200,
            "height": 100,
            "zIndex": 10,
            "connector": "smooth",
            "data": {
              "type": "tm.Boundary",
              "name": "Trust Boundary",
              "description": "",
              "isTrustBoundary": true,
              "hasOpenThreats": false,
              "crossingFlows": [],
              "containedElements": []
            },
            "labels": [
              "Trust Boundary"
            ],
            "id": "196fae91-b267-46dd-a698-5c4cfc2abf1b",
            "source": {
              "x": 199,
              "y": -1920
            },
            "target": {
              "x": 299,
              "y": -1820
            }
          },
          {
            "position": {
              "x": 330,
              "y": -1910
            },
            "size": {
              "width": 60,
              "height": 60
            },
            "attrs": {
              "text": {
                "text": "Web Servlet"
              },
              "body": {
                "stroke": "#333333",
                "strokeWidth": 1.5,
                "strokeDasharray": null
              }
            },
            "visible": true,
            "shape": "process",
            "zIndex": 11,
            "ports": {
              "groups": {
                "top": {
                  "position": "top",
                  "attrs": {
                    "circle": {
                      "r": 4,
                      "magnet": true,
                      "stroke": "#5F95FF",
                      "strokeWidth": 1,
                      "fill": "#fff",
                      "style": {
                        "visibility": "hidden"
                      }
                    }
                  }
                },
                "right": {
                  "position": "right",
                  "attrs": {
                    "circle": {
                      "r": 4,
                      "magnet": true,
                      "stroke": "#5F95FF",
                      "strokeWidth": 1,
                      "fill": "#fff",
                      "style": {
                        "visibility": "hidden"
                      }
                    }
                  }
                },
                "bottom": {
                  "position": "bottom",
                  "attrs": {
                    "circle": {
                      "r": 4,
                      "magnet": true,
                      "stroke": "#5F95FF",
                      "strokeWidth": 1,
                      "fill": "#fff",
                      "style": {
                        "visibility": "hidden"
                      }
                    }
                  }
                },
                "left": {
                  "position": "left",
                  "attrs": {
                    "circle": {
                      "r": 4,
                      "magnet": true,
                      "stroke": "#5F95FF",
                      "strokeWidth": 1,
                      "fill": "#fff",
                      "style": {
                        "visibility": "hidden"
                      }
                    }
                  }
                }
              },
              "items": [
                {
                  "group": "top",
                  "id": "2a2d08b1-243b-4b80-a482-570aa7ad80fc"
                },
                {
                  "group": "right",
                  "id": "990b81b1-9354-4c2f-a340-b643f5d050af"
                },
                {
                  "group": "bottom",
                  "id": "58b1bc7a-806e-45a3-84e2-0af62650c853"
                },
                {
                  "group": "left",
                  "id": "0dac111f-126c-4a36-bf12-2b23490551f2"
                }
              ]
            },
            "id": "2502d73f-235a-459e-bf50-445ebe2314dc",
            "data": {
              "type": "tm.Process",
              "name": "Web Servlet",
              "description": "",
              "outOfScope": false,
              "isTrustBoundary": false,
              "reasonOutOfScope": "",
              "hasOpenThreats": false,
              "handlesCardPayment": false,
              "handlesGoodsOrServices": false,
              "isWebApplication": false,
              "privilegeLevel": "",
              "threats": []
            }
          },
          {
            "position": {
              "x": 86,
              "y": -1920
            },
            "size": {
              "width": 112.5,
              "height": 60
            },
            "attrs": {
              "text": {
                "text": "Users"
              },
              "body": {
                "stroke": "#333333",
                "strokeWidth": 1.5,
                "strokeDasharray": null
              }
            },
            "visible": true,
            "shape": "actor",
            "zIndex": 12,
            "ports": {
              "groups": {
                "top": {
                  "position": "top",
                  "attrs": {
                    "circle": {
                      "r": 4,
                      "magnet": true,
                      "stroke": "#5F95FF",
                      "strokeWidth": 1,
                      "fill": "#fff",
                      "style": {
                        "visibility": "hidden"
                      }
                    }
                  }
                },
                "right": {
                  "position": "right",
                  "attrs": {
                    "circle": {
                      "r": 4,
                      "magnet": true,
                      "stroke": "#5F95FF",
                      "strokeWidth": 1,
                      "fill": "#fff",
                      "style": {
                        "visibility": "hidden"
                      }
                    }
                  }
                },
                "bottom": {
                  "position": "bottom",
                  "attrs": {
                    "circle": {
                      "r": 4,
                      "magnet": true,
                      "stroke": "#5F95FF",
                      "strokeWidth": 1,
                      "fill": "#fff",
                      "style": {
                        "visibility": "hidden"
                      }
                    }
                  }
                },
                "left": {
                  "position": "left",
                  "attrs": {
                    "circle": {
                      "r": 4,
                      "magnet": true,
                      "stroke": "#5F95FF",
                      "strokeWidth": 1,
                      "fill": "#fff",
                      "style": {
                        "visibility": "hidden"
                      }
                    }
                  }
                }
              },
              "items": [
                {
                  "group": "top",
                  "id": "55f11b51-a8a0-4fbc-ba84-3b7f2bb0f054"
                },
                {
                  "group": "right",
                  "id": "5a024b05-887b-4fc2-9cb0-05b48dc467a1"
                },
                {
                  "group": "bottom",
                  "id": "2c88b912-25d7-487b-af35-060553a6d2e9"
                },
                {
                  "group": "left",
                  "id": "45d69653-4a6c-45fc-9a61-b0ed9f77c8fa"
                }
              ]
            },
            "id": "c61e27b8-7929-4150-aef0-26fb724875cb",
            "data": {
              "type": "tm.Actor",
              "name": "Users",
              "description": "",
              "isTrustBoundary": false,
              "outOfScope": false,
              "reasonOutOfScope": "",
              "hasOpenThreats": false,
              "providesAuthentication": false,
              "threats": []
            }
          },
          {
            "position": {
              "x": 542,
              "y": -1910
            },
            "size": {
              "width": 60,
              "height": 60
            },
            "attrs": {
              "text": {
                "text": "Login Process"
              },
              "body": {
                "stroke": "#333333",
                "strokeWidth": 1.5,
                "strokeDasharray": null
              }
            },
            "visible": true,
            "shape": "process",
            "zIndex": 13,
            "ports": {
              "groups": {
                "top": {
                  "position": "top",
                  "attrs": {
                    "circle": {
                      "r": 4,
                      "magnet": true,
                      "stroke": "#5F95FF",
                      "strokeWidth": 1,
                      "fill": "#fff",
                      "style": {
                        "visibility": "hidden"
                      }
                    }
                  }
                },
                "right": {
                  "position": "right",
                  "attrs": {
                    "circle": {
                      "r": 4,
                      "magnet": true,
                      "stroke": "#5F95FF",
                      "strokeWidth": 1,
                      "fill": "#fff",
                      "style": {
                        "visibility": "hidden"
                      }
                    }
                  }
                },
                "bottom": {
                  "position": "bottom",
                  "attrs": {
                    "circle": {
                      "r": 4,
                      "magnet": true,
                      "stroke": "#5F95FF",
                      "strokeWidth": 1,
                      "fill": "#fff",
                      "style": {
                        "visibility": "hidden"
                      }
                    }
                  }
                },
                "left": {
                  "position": "left",
                  "attrs": {
                    "circle": {
                      "r": 4,
                      "magnet": true,
                      "stroke": "#5F95FF",
                      "strokeWidth": 1,
                      "fill": "#fff",
                      "style": {
                        "visibility": "hidden"
                      }
                    }
                  }
                }
              },
              "items": [
                {
                  "group": "top",
                  "id": "2a2d08b1-243b-4b80-a482-570aa7ad80fc"
                },
                {
                  "group": "right",
                  "id": "990b81b1-9354-4c2f-a340-b643f5d050af"
                },
                {
                  "group": "bottom",
                  "id": "58b1bc7a-806e-45a3-84e2-0af62650c853"
                },
                {
                  "group": "left",
                  "id": "0dac111f-126c-4a36-bf12-2b23490551f2"
                }
              ]
            },
            "id": "4d84b8f4-ae10-4bfb-b57b-d267530e4ce3",
            "data": {
              "type": "tm.Process",
              "name": "Login Process",
              "description": "",
              "outOfScope": false,
              "isTrustBoundary": false,
              "reasonOutOfScope": "",
              "hasOpenThreats": false,
              "handlesCardPayment": false,
              "handlesGoodsOrServices": false,
              "isWebApplication": false,
              "privilegeLevel": "",
              "threats": [
                {
                  "id": "31e6b457-127b-4f7a-a143-a50669d09d88",
                  "title": "Login Process",
                  "status": "Mitigated",
                  "severity": "Critical",
                  "type": "Tampering",
                  "description": "Attacker can inject malicious SQL to bypass login",
                  "mitigation": "BCrypt hashing strength 12 applied",
                  "modelType": "STRIDE",
                  "new": false,
                  "number": 1,
                  "score": ""
                },
                {
                  "id": "0f2b89c5-dd7e-47fb-a23c-897ebbf79296",
                  "title": "Users",
                  "status": "Mitigated",
                  "severity": "High",
                  "type": "Spoofing",
                  "description": "Attacker user ki identity chura kar ya fake credentials ke zariye login kar sakta hai",
                  "mitigation": "BCrypt password hashing (strength 12) aur logout par session invalidation ka istemal kiya gaya hai.",
                  "modelType": "STRIDE",
                  "new": false,
                  "number": 2,
                  "score": ""
                },
                {
                  "id": "3d33376d-b256-4493-92b0-bb65de8fd20b",
                  "title": "Web Servlet",
                  "status": "Mitigated",
                  "severity": "High",
                  "type": "Information disclosure",
                  "description": " System error ya crash hone par sensitive stack trace ya internal details leak ho sakti hain.",
                  "mitigation": "Custom error pages banaye gaye hain jo sirf generic message dikhate hain aur stack trace ko hide rakhte hain (server.error.include-stacktrace=never)",
                  "modelType": "STRIDE",
                  "new": false,
                  "number": 3,
                  "score": ""
                },
                {
                  "id": "d5a99aed-ee31-4a94-9ab5-c150bd9935bc",
                  "title": "H2 Database",
                  "status": "Mitigated",
                  "severity": "High",
                  "type": "Information disclosure",
                  "description": " Agar database connection secure na ho to data unauthorized taur par badla ja sakta hai.",
                  "mitigation": "Parameterized queries aur Spring Data JPA ka istemal taake koi direct SQL manipulation na kar sake",
                  "modelType": "STRIDE",
                  "new": false,
                  "number": 4,
                  "score": ""
                },
                {
                  "id": "861dafcc-8959-4d29-925f-c6d68fc59134",
                  "title": "Data Flow",
                  "status": "Mitigated",
                  "severity": "High",
                  "type": "Information disclosure",
                  "description": "Login request ka data (password) raste mein intercept (hijack) ho sakta hai.",
                  "mitigation": "HTTPS aur secure cookie flags (HttpOnly, Secure, SameSite=Strict) ka istemal.",
                  "modelType": "STRIDE",
                  "new": false,
                  "number": 5,
                  "score": ""
                }
              ],
              "threatFrequency": {
                "spoofing": 3,
                "tampering": 4,
                "repudiation": 0,
                "informationDisclosure": 3,
                "denialOfService": 0,
                "elevationOfPrivilege": 0
              }
            }
          },
          {
            "position": {
              "x": 730,
              "y": -1920
            },
            "size": {
              "width": 120,
              "height": 60
            },
            "attrs": {
              "text": {
                "text": "H2 Database"
              },
              "topLine": {
                "strokeWidth": 1.5,
                "strokeDasharray": null
              },
              "bottomLine": {
                "strokeWidth": 1.5,
                "strokeDasharray": null
              }
            },
            "visible": true,
            "shape": "store",
            "zIndex": 14,
            "ports": {
              "groups": {
                "top": {
                  "position": "top",
                  "attrs": {
                    "circle": {
                      "r": 4,
                      "magnet": true,
                      "stroke": "#5F95FF",
                      "strokeWidth": 1,
                      "fill": "#fff",
                      "style": {
                        "visibility": "hidden"
                      }
                    }
                  }
                },
                "right": {
                  "position": "right",
                  "attrs": {
                    "circle": {
                      "r": 4,
                      "magnet": true,
                      "stroke": "#5F95FF",
                      "strokeWidth": 1,
                      "fill": "#fff",
                      "style": {
                        "visibility": "hidden"
                      }
                    }
                  }
                },
                "bottom": {
                  "position": "bottom",
                  "attrs": {
                    "circle": {
                      "r": 4,
                      "magnet": true,
                      "stroke": "#5F95FF",
                      "strokeWidth": 1,
                      "fill": "#fff",
                      "style": {
                        "visibility": "hidden"
                      }
                    }
                  }
                },
                "left": {
                  "position": "left",
                  "attrs": {
                    "circle": {
                      "r": 4,
                      "magnet": true,
                      "stroke": "#5F95FF",
                      "strokeWidth": 1,
                      "fill": "#fff",
                      "style": {
                        "visibility": "hidden"
                      }
                    }
                  }
                }
              },
              "items": [
                {
                  "group": "top",
                  "id": "bbdc8b1a-29fa-4c95-934d-f6abf8055d14"
                },
                {
                  "group": "right",
                  "id": "dacee592-1a4b-461b-8225-1f5ef9080236"
                },
                {
                  "group": "bottom",
                  "id": "db9e73fb-4535-4924-96f1-e426fa2ebf23"
                },
                {
                  "group": "left",
                  "id": "b84ce6fb-d361-4789-b422-f2184d977b09"
                }
              ]
            },
            "id": "c1e90d91-4ce7-4b88-b12b-e6b396b4d9f8",
            "data": {
              "type": "tm.Store",
              "name": "H2 Database",
              "description": "",
              "outOfScope": false,
              "isTrustBoundary": false,
              "reasonOutOfScope": "",
              "hasOpenThreats": false,
              "isALog": false,
              "isEncrypted": false,
              "isSigned": false,
              "storesCredentials": false,
              "storesInventory": false,
              "threats": []
            }
          }
        ],
        "description": ""
      }
    ],
    "diagramTop": 2,
    "reviewer": "",
    "threatTop": 5
  }
}